napari_bruce/__init__.py
napari_bruce/cli.py
napari_bruce/configuration.py
napari_bruce/napari.yaml
napari_bruce/widget.py
napari_bruce/workflow.py
napari_bruce/bioformats/__init__.py
napari_bruce/bioformats/bioformats_package.jar
napari_bruce/stardist_models/__init__.py
napari_bruce/stardist_models/stardist_psyn/config.json
napari_bruce/stardist_models/stardist_psyn/thresholds.json
napari_bruce/stardist_models/stardist_psyn/weights_best.h5
napari_bruce/stardist_models/stardist_psyn/weights_last.h5
napari_bruce/stardist_models/stardist_psyn/logs/images/events.out.tfevents.1761568569.LIN-RWM005.1274739.3.v2
napari_bruce/stardist_models/stardist_psyn/logs/train/events.out.tfevents.1761568569.LIN-RWM005.1274739.4.v2
napari_bruce/stardist_models/stardist_psyn/logs/validation/events.out.tfevents.1761568576.LIN-RWM005.1274739.5.v2
napari_bruce/stardist_models/stardist_th/config.json
napari_bruce/stardist_models/stardist_th/thresholds.json
napari_bruce/stardist_models/stardist_th/weights_best.h5
napari_bruce/stardist_models/stardist_th/weights_last.h5
napari_bruce/stardist_models/stardist_th/logs/images/events.out.tfevents.1761567655.LIN-RWM005.1274739.0.v2
napari_bruce/stardist_models/stardist_th/logs/train/events.out.tfevents.1761567655.LIN-RWM005.1274739.1.v2
napari_bruce/stardist_models/stardist_th/logs/validation/events.out.tfevents.1761567663.LIN-RWM005.1274739.2.v2
napari_bruce-0.0.5.dist-info/METADATA
napari_bruce-0.0.5.dist-info/WHEEL
napari_bruce-0.0.5.dist-info/entry_points.txt
napari_bruce-0.0.5.dist-info/top_level.txt
napari_bruce-0.0.5.dist-info/RECORD
