Metadata-Version: 2.4
Name: napari-bruce
Version: 0.0.5
Summary: A napari plugin for drawing PALM RoboSoftware elements using StarDist segmentation
Author-email: Benjamin Vallin <ben.vallin@gmail.com>
License: MIT
Classifier: Framework :: napari
Classifier: Programming Language :: Python :: 3
Classifier: Programming Language :: Python :: 3.10
Classifier: Operating System :: OS Independent
Classifier: License :: OSI Approved :: MIT License
Classifier: Intended Audience :: Science/Research
Requires-Python: >=3.9
Requires-Dist: napari
Requires-Dist: PyQt5
Requires-Dist: qtpy
Requires-Dist: numpy==1.26.4
Requires-Dist: opencv-python-headless
Requires-Dist: ome-types
Requires-Dist: tifffile
Requires-Dist: pandas
Requires-Dist: matplotlib
Requires-Dist: csbdeep
Requires-Dist: stardist
